devco/__init__.py
devco/cli.py
devco/embeddings.py
devco/principles.py
devco/sections.py
devco/storage.py
devco/summary.py
devco-0.1.8.dist-info/licenses/LICENSE
devco-0.1.8.dist-info/METADATA
devco-0.1.8.dist-info/WHEEL
devco-0.1.8.dist-info/entry_points.txt
devco-0.1.8.dist-info/top_level.txt
devco-0.1.8.dist-info/RECORD
