Metadata-Version: 2.4
Name: devco
Version: 0.1.8
Summary: A CLI tool that helps AI assistants understand projects through persistent documentation and RAG search
Home-page: https://github.com/lorenzowood/devco
Author: Claude Code
Author-email: Claude Code <noreply@anthropic.com>
License: MIT
Project-URL: Homepage, https://github.com/lorenzowood/devco
Project-URL: Repository, https://github.com/lorenzowood/devco
Project-URL: Bug Reports, https://github.com/lorenzowood/devco/issues
Project-URL: Documentation, https://github.com/lorenzowood/devco/wiki
Keywords: documentation,ai,assistant,rag,vector,search,embeddings,cli,development
Classifier: Development Status :: 4 - Beta
Classifier: Intended Audience :: Developers
Classifier: Topic :: Software Development :: Documentation
Classifier: Topic :: Software Development :: Libraries :: Python Modules
Classifier: License :: OSI Approved :: MIT License
Classifier: Programming Language :: Python :: 3
Classifier: Programming Language :: Python :: 3.8
Classifier: Programming Language :: Python :: 3.9
Classifier: Programming Language :: Python :: 3.10
Classifier: Programming Language :: Python :: 3.11
Classifier: Programming Language :: Python :: 3.12
Classifier: Operating System :: OS Independent
Requires-Python: >=3.8
License-File: LICENSE
Requires-Dist: llm>=0.13.0
Requires-Dist: llm-gemini
Requires-Dist: sqlite-utils>=3.0.0
Requires-Dist: python-dotenv>=1.0.0
Requires-Dist: numpy>=1.20.0
Provides-Extra: dev
Requires-Dist: pytest>=7.0.0; extra == "dev"
Requires-Dist: pytest-mock>=3.0.0; extra == "dev"
Dynamic: author
Dynamic: home-page
Dynamic: license-file
Dynamic: requires-python
